padtools/__init__.py
padtools/regions/__init__.py
padtools/regions/region.py
padtools/regions/data/regions.json
padtools/servers/__init__.py
padtools/servers/asset.py
padtools/servers/extlist.py
padtools/servers/http_interface.py
padtools/servers/server.py
padtools/servers/data/servers.json
padtools-0.1.2.dist-info/DESCRIPTION.rst
padtools-0.1.2.dist-info/METADATA
padtools-0.1.2.dist-info/RECORD
padtools-0.1.2.dist-info/WHEEL
padtools-0.1.2.dist-info/metadata.json
padtools-0.1.2.dist-info/top_level.txt
