Metadata-Version: 2.0
Name: padtools
Version: 0.1.2
Summary: A package for the popular iOS & Android game "Puzzle & Dragons" (PAD)
Home-page: https://github.com/codywatts/padtools
Author: Cody Watts
Author-email: cody@codywatts.com
License: GPLv3
